[{"courseID":"CS103","title":"Algorithm","credits":4,"departmentID":"D001","roomID":"R103","enrollments":null,"assignments":null},{"courseID":"CS104","title":"Operating Systems","credits":6,"departmentID":"D002","roomID":"R201","enrollments":[],"assignments":[]},{"courseID":"CS101","title":"Introduction to Programming","credits":5,"departmentID":"D001","roomID":"R101","enrollments":[],"assignments":[]},{"courseID":"CS102","title":"Data Structures","credits":4,"departmentID":"D001","roomID":"R102","enrollments":[],"assignments":[]}]